colemen_linux_utilities.py
colemen_linux_utils/ColemenLinuxUtils.py
colemen_linux_utils/__init__.py
colemen_linux_utils/clipboard.py
colemen_linux_utils/keys.py
colemen_linux_utils/settings/__init__.py
colemen_linux_utils/settings/control.py
colemen_linux_utils/settings/types.py
colemen_linux_utils-0.0.3.dist-info/METADATA
colemen_linux_utils-0.0.3.dist-info/WHEEL
colemen_linux_utils-0.0.3.dist-info/top_level.txt
colemen_linux_utils-0.0.3.dist-info/RECORD
